application_framework/__init__.py
application_framework/utils.py
application_framework/actor/__init__.py
application_framework/actor/actor.py
application_framework/config/__init__.py
application_framework/config/builder.py
application_framework/config/config.py
application_framework/host/__init__.py
application_framework/host/builder.py
application_framework/host/host.py
application_framework/messaging/__init__.py
application_framework/messaging/channels.py
application_framework/messaging/message.py
application_framework/messaging/message_queue.py
application_framework/service/__init__.py
application_framework/service/cancellation_token.py
application_framework/service/cancellation_token_source.py
application_framework/service/execution_mode.py
application_framework/service/service.py
application_framework/service/service_config.py
application_framework/service/application/__init__.py
application_framework/service/application/builder.py
application_framework/supervisor/__init__.py
application_framework/supervisor/restart_strategy.py
application_framework/supervisor/supervisor.py
py_application_framework-1.0.0a5.dist-info/LICENSE
py_application_framework-1.0.0a5.dist-info/METADATA
py_application_framework-1.0.0a5.dist-info/WHEEL
py_application_framework-1.0.0a5.dist-info/entry_points.txt
py_application_framework-1.0.0a5.dist-info/top_level.txt
py_application_framework-1.0.0a5.dist-info/RECORD
